ipdbx/__init__.py
ipdbx/__main__.py
ipdbx/stdout.py
ipdbx-1.0.4.dist-info/AUTHORS
ipdbx-1.0.4.dist-info/COPYING.txt
ipdbx-1.0.4.dist-info/LICENSE
ipdbx-1.0.4.dist-info/METADATA
ipdbx-1.0.4.dist-info/WHEEL
ipdbx-1.0.4.dist-info/entry_points.txt
ipdbx-1.0.4.dist-info/top_level.txt
ipdbx-1.0.4.dist-info/zip-safe
ipdbx-1.0.4.dist-info/RECORD
