Metadata-Version: 2.1
Name: ipdbx
Version: 1.0.4
Summary: IPython-enabled pdb with extra functionality and customisation
Home-page: https://github.com/giladbarnea/ipdbx
Author: Gilad Barnea
Author-email: giladbrn@gmail.com
License: BSD
Keywords: pdb ipython ipdb ipdbx ipdb-extended
Platform: UNKNOWN
Classifier: Programming Language :: Python :: 3.6
Classifier: Programming Language :: Python :: 3.7
Classifier: Programming Language :: Python :: 3.8
Classifier: Operating System :: MacOS :: MacOS X
Classifier: Operating System :: POSIX :: Linux
Classifier: Operating System :: Microsoft :: Windows
Classifier: Topic :: Software Development :: Debuggers
Classifier: License :: OSI Approved :: BSD License
Requires-Python: >=3.6
Requires-Dist: IPython (>=7.0)
